{
  "log_file": "logs\\training\\crypto\\TRUMP-USDT\\1d\\training_log.json",
  "total_events": 1,
  "events": [
    {
      "timestamp": "2026-01-19T07:13:36.453809Z",
      "level": "ERROR",
      "message": "Training skipped: crypto/TRUMP-USDT (short): insufficient data (162 rows, need 200)",
      "category": "TRAIN",
      "symbol": "TRUMP-USDT",
      "asset_type": "crypto",
      "data": {
        "error": "insufficient data (162 rows, need 200)",
        "horizon": "short"
      }
    }
  ]
}