{
  "log_file": "logs\\training\\crypto\\YFI-USDC\\1d\\training_log.json",
  "total_events": 1,
  "events": [
    {
      "timestamp": "2026-01-17T13:26:20.095390Z",
      "level": "ERROR",
      "message": "Training skipped: crypto/YFI-USDC (intraday): No data.json found for crypto/YFI-USDC/1d",
      "category": "TRAIN",
      "symbol": "YFI-USDC",
      "asset_type": "crypto",
      "data": {
        "error": "No data.json found for crypto/YFI-USDC/1d",
        "horizon": "intraday"
      }
    }
  ]
}