{
  "asset_type": "crypto",
  "symbol": "LTC-BTC",
  "timeframe": "1d",
  "last_updated": "2026-01-19T00:00:00+00:00",
  "feature_count": 159,
  "features": {
    "SMA_5": {
      "value": 0.0007714
    },
    "SMA_10": {
      "value": 0.0008066
    },
    "SMA_20": {
      "value": 0.0008513500000000001
    },
    "SMA_50": {
      "value": 0.00087756
    },
    "SMA_100": {
      "value": 0.0008995
    },
    "SMA_200": {
      "value": 0.0009317
    },
    "EMA_9": {
      "value": 0.0007969992237618792
    },
    "EMA_12": {
      "value": 0.0008093868590807647
    },
    "EMA_26": {
      "value": 0.0008435573016147091
    },
    "EMA_50": {
      "value": 0.0008707871444463516
    },
    "EMA_100": {
      "value": 0.0008967084131928248
    },
    "EMA_200": {
      "value": 0.0009234929518938263
    },
    "WMA_14": {
      "value": 0.0008040952380952382
    },
    "Hull_MA": {
      "value": 0.0007646919913419912
    },
    "VWMA": {
      "value": 0.0008329309315815481
    },
    "VWAP": {
      "value": 0.006585267463822693
    },
    "Session_VWAP": {
      "value": 0.006585267463822693
    },
    "MACD": {
      "value": -3.417044253394442e-05
    },
    "MACD_signal": {
      "value": -2.3046432045698665e-05
    },
    "MACD_histogram": {
      "value": -1.1124010488245754e-05
    },
    "RSI_7": {
      "value": 22.260799454770634
    },
    "RSI_14": {
      "value": 27.613844128898222
    },
    "RSI_21": {
      "value": 32.10094800912972
    },
    "Momentum_roc_1": {
      "value": -0.020725388601036232
    },
    "Momentum_roc_7": {
      "value": -0.09352517985611508
    },
    "Momentum_roc_14": {
      "value": -0.14960629921259838
    },
    "Rate_of_Change": {
      "value": -0.1590656284760844
    },
    "TRIX": {
      "value": -0.00350893615578729
    },
    "TSI": {
      "value": -34.810899548380974
    },
    "Stochastic_%K": {
      "value": 26.666666666666693
    },
    "Stochastic_%D": {
      "value": 28.014571948998192
    },
    "Williams_%R": {
      "value": -73.33333333333331
    },
    "CCI_20": {
      "value": -145.27475444650943
    },
    "ATR_14": {
      "value": 3.4642857142857144e-05
    },
    "ATR_7": {
      "value": 4.5857142857142875e-05
    },
    "Bollinger_Bands_upper_20_2": {
      "value": 0.0009647069583232976
    },
    "Bollinger_Bands_lower_20_2": {
      "value": 0.0007379930416767025
    },
    "Bollinger_Bandwidth": {
      "value": 0.2662993089171259
    },
    "Bollinger_%b": {
      "value": 0.07942590640065142
    },
    "Keltner_Channel_upper": {
      "value": 0.0008937607823205014
    },
    "Keltner_Channel_lower": {
      "value": 0.0007705607823205015
    },
    "Donchian_Channel_high": {
      "value": 0.000919
    },
    "Donchian_Channel_low": {
      "value": 0.0007
    },
    "ADX_14": {
      "value": 46.46042775735383
    },
    "DI_plus": {
      "value": 54.84536082474266
    },
    "DI_minus": {
      "value": 707.2164948453608
    },
    "RSI_Band_Cross": {
      "value": 1.0
    },
    "ROC_Signal": {
      "value": -0.09352517985611508
    },
    "Rolling_Volatility_7": {
      "value": 0.02858332920815161
    },
    "Rolling_Volatility_14": {
      "value": 0.023519255636156602
    },
    "Rolling_Volatility_30": {
      "value": 0.02069239784767265
    },
    "Realized_Volatility": {
      "value": 0.1151885690466772
    },
    "Historical_Volatility": {
      "value": 0.11333693070041657
    },
    "Rolling_Skew": {
      "value": 0.26442039124865585
    },
    "Rolling_Kurtosis": {
      "value": 0.2739282809837665
    },
    "Volatility_Skew": {
      "value": 0.007890931360478963
    },
    "Volatility_Clustering": {
      "value": 0.5564907815266311
    },
    "ZScore_returns_7": {
      "value": -0.24995730018073592
    },
    "ZScore_returns_30": {
      "value": -0.7657496522026898
    },
    "Normalized_Returns": {
      "value": -0.7657496522026898
    },
    "Log_Returns": {
      "value": -0.020943173845243135
    },
    "Return_1": {
      "value": -0.020725388601036232
    },
    "Return_3": {
      "value": -0.03939008894536211
    },
    "Return_7": {
      "value": -0.09352517985611508
    },
    "Cumulative_Return_30": {
      "value": -0.14188422247446064
    },
    "Rolling_Sharpe_30": {
      "value": -0.23584468952640547
    },
    "Rolling_Sharpe_90": {
      "value": -0.03179617908926481
    },
    "Max_Drawdown_30": {
      "value": -0.173960612691466
    },
    "Drawdown_Duration": {
      "value": 65.0
    },
    "OBV": {
      "value": -20243062.829
    },
    "CMF": {
      "value": -0.16613358528280756
    },
    "MFI": {
      "value": 26.718752393104367
    },
    "Ease_of_Movement": {
      "value": -1.8382896561885602e-08
    },
    "Force_Index": {
      "value": -0.4956577759999986
    },
    "Accumulation_Distribution": {
      "value": -10566129.833976131
    },
    "Chaikin_Oscillator": {
      "value": -12849.258164197206
    },
    "Volume_Change_1": {
      "value": 1.8687854279168672
    },
    "Volume_Change_7": {
      "value": 0.04731514067394871
    },
    "Volume_Ratio": {
      "value": 1.5910879976984174
    },
    "Volume_Surge_Flag": {
      "value": 1.0
    },
    "Price_Lag_1": {
      "value": 0.000772
    },
    "Price_Lag_2": {
      "value": 0.000787
    },
    "Price_Lag_3": {
      "value": 0.000787
    },
    "Close_Lag_1": {
      "value": 0.000772
    },
    "Close_Lag_2": {
      "value": 0.000787
    },
    "Close_Lag_3": {
      "value": 0.000787
    },
    "Close_Lag_4": {
      "value": 0.000755
    },
    "Close_Lag_5": {
      "value": 0.000791
    },
    "Close_Lag_6": {
      "value": 0.00082
    },
    "Close_Lag_7": {
      "value": 0.000834
    },
    "Close_Lag_8": {
      "value": 0.000866
    },
    "Close_Lag_9": {
      "value": 0.000898
    },
    "Close_Lag_10": {
      "value": 0.000899
    },
    "Open_Lag_1": {
      "value": 0.000787
    },
    "High_Lag_1": {
      "value": 0.000797
    },
    "Low_Lag_1": {
      "value": 0.000764
    },
    "Typical_Price": {
      "value": 0.0007426666666666666
    },
    "Median_Price": {
      "value": 0.000736
    },
    "Price_Range": {
      "value": 7.200000000000002e-05
    },
    "Intraday_Range": {
      "value": -1.5999999999999955e-05
    },
    "Gap_Open": {
      "value": 0.0
    },
    "Gap_Percentage": {
      "value": 0.0
    },
    "Donchian_Breakout_Flag": {
      "value": 0.0
    },
    "MA_Crossover_Signal": {
      "value": 0.0
    },
    "MACD_Crossover_Signal": {
      "value": 0.0
    },
    "Volatility_Expansion_Flag": {
      "value": 1.0
    },
    "Ichimoku_Tenkan": {
      "value": 0.0008005
    },
    "Ichimoku_Kijun": {
      "value": 0.0008095
    },
    "Ichimoku_Senkou_Span_A": {
      "value": 0.0008945
    },
    "Ichimoku_Senkou_Span_B": {
      "value": 0.0009715
    },
    "Parabolic_SAR": {
      "value": 0.0007
    },
    "Price_Channel_Slope": {
      "value": -2.9500000000000014e-06
    },
    "Fractal_High": {
      "value": 0.000898
    },
    "Fractal_Low": {
      "value": 0.00086
    },
    "Pivot_Point": {
      "value": 0.0007776666666666666
    },
    "Pivot_R1": {
      "value": 0.0007913333333333332
    },
    "Pivot_S1": {
      "value": 0.0007583333333333333
    },
    "Pivot_R2": {
      "value": 0.0008106666666666666
    },
    "Pivot_S2": {
      "value": 0.0007446666666666667
    },
    "Fibonacci_Level_0.236": {
      "value": 0.000867316
    },
    "Fibonacci_Level_0.382": {
      "value": 0.000835342
    },
    "Fibonacci_Level_0.5": {
      "value": 0.0008095
    },
    "Fibonacci_Level_0.618": {
      "value": 0.000783658
    },
    "Fibonacci_Level_0.786": {
      "value": 0.000746866
    },
    "Seasonality_Monthly": {
      "value": 1.0
    },
    "Seasonality_DayOfMonth": {
      "value": 19.0
    },
    "Day_of_Week": {
      "value": 0.0
    },
    "Hour_of_Day": {
      "value": 0.0
    },
    "Is_Holiday_Flag": {
      "value": 0.0
    },
    "Feature_Interaction_Terms": {
      "value": -0.0035186287959604354
    },
    "Ensemble_Feature_Aggregates": {
      "value": -0.1632074449747319
    },
    "dxy_index": {
      "value": 0.0
    },
    "dxy_index_return_5": {
      "value": 0.0
    },
    "dxy_index_zscore_60": {
      "value": 0.0
    },
    "vix_index": {
      "value": 0.0
    },
    "vix_index_return_5": {
      "value": 0.0
    },
    "vix_index_zscore_60": {
      "value": 0.0
    },
    "us10y_yield": {
      "value": 0.0
    },
    "us10y_yield_return_5": {
      "value": 0.0
    },
    "us10y_yield_zscore_60": {
      "value": 0.0
    },
    "us2y_yield": {
      "value": 0.0
    },
    "us2y_yield_return_5": {
      "value": 0.0
    },
    "us2y_yield_zscore_60": {
      "value": 0.0
    },
    "tips_etf": {
      "value": 0.0
    },
    "tips_etf_return_5": {
      "value": 0.0
    },
    "tips_etf_zscore_60": {
      "value": 0.0
    },
    "real_yield_spread": {
      "value": 0.0
    },
    "yield_curve_2s10s": {
      "value": 0.0
    },
    "gvz_gold_vol": {
      "value": 0.0
    },
    "gvz_gold_vol_pct_change": {
      "value": 0.0
    },
    "gvz_gold_vol_zscore": {
      "value": 0.0
    },
    "ovx_crude_vol": {
      "value": 0.0
    },
    "ovx_crude_vol_pct_change": {
      "value": 0.0
    },
    "ovx_crude_vol_zscore": {
      "value": 0.0
    },
    "trend_strength_60": {
      "value": -0.2110602060474507
    },
    "volatility_cluster_20": {
      "value": 1.0501099844540913
    },
    "mean_reversion_flag": {
      "value": 0.0
    },
    "volatility_regime_state": {
      "value": 1.0
    },
    "drawdown_lookback_90": {
      "value": -0.2901408450704225
    }
  }
}