{
  "asset_type": "crypto",
  "symbol": "SHIB-USDT",
  "timeframe": "1d",
  "training_samples": 1125,
  "validation_samples": 187,
  "feature_count": 61,
  "feature_sample": [
    "target_quantile_bin",
    "target_return_smoothed",
    "target_direction",
    "Volume_Change_7",
    "Volume_Ratio",
    "Return_3",
    "Chaikin_Oscillator",
    "Volume_Surge_Flag",
    "CMF",
    "Momentum_roc_7",
    "RSI_Band_Cross",
    "CCI_20",
    "Stochastic_%D",
    "RSI_14",
    "RSI_21",
    "Bollinger_%b",
    "RSI_7",
    "Volatility_Skew",
    "volatility_regime_state",
    "TSI",
    "Max_Drawdown_30",
    "Volatility_Clustering",
    "Rolling_Volatility_30",
    "Realized_Volatility",
    "Williams_%R"
  ],
  "config": {
    "learning_rate": 0.0005,
    "buffer_size": 2000,
    "learning_starts": 200,
    "batch_size": 128,
    "gamma": 0.97,
    "exploration_fraction": 0.15,
    "exploration_final_eps": 0.1,
    "target_update_interval": 200
  },
  "metrics": {
    "model_name": "DQN",
    "mae": null,
    "rmse": null,
    "r2": null,
    "directional_accuracy": null,
    "mean_predicted_return": null,
    "mean_actual_return": null,
    "notes": "RL metrics tracked separately",
    "precision": null,
    "recall": null,
    "f1": null,
    "roc_auc": null,
    "action": "short",
    "action_reason": "Action selected directly by DQN policy on latest state; reward history tracked separately.",
    "validation_policy_metrics": {
      "total_return": 5.494885964796187,
      "avg_return": 0.029542397660194553,
      "sharpe": 15.319146249630872,
      "hit_rate": 0.8709677419354839,
      "max_drawdown": -0.016150740242261152
    },
    "test_policy_metrics": {
      "total_return": 4.9240997527161685,
      "avg_return": 0.02647365458449553,
      "sharpe": 16.10550375598335,
      "hit_rate": 0.9139784946236559,
      "max_drawdown": -0.01351738525730184
    },
    "predicted_return": -0.02647365458449553,
    "predicted_price": 8.537826049293974e-06
  }
}